smartprofiler/__init__.py
smartprofiler/base_profiler.py
smartprofiler/cpu_profiler.py
smartprofiler/cpu_time.py
smartprofiler/disk_profiler.py
smartprofiler/disk_usage.py
smartprofiler/function_profiler.py
smartprofiler/function_tracking.py
smartprofiler/logger_adapter.py
smartprofiler/memory.py
smartprofiler/memory_profiler.py
smartprofiler/network_profiler.py
smartprofiler/network_usage.py
smartprofiler/time.py
smartprofiler/visualizer.py
tests/__init__.py
tests/test_cpu_time.py
tests/test_function_tracking.py
tests/test_logger_adapter.py
tests/test_memory.py
tests/test_profilers.py
tests/test_time.py
smartprofiler-1.2.0.dist-info/METADATA
smartprofiler-1.2.0.dist-info/WHEEL
smartprofiler-1.2.0.dist-info/top_level.txt
smartprofiler-1.2.0.dist-info/RECORD
