Metadata-Version: 2.1
Name: smartprofiler
Version: 1.2.0
Summary: A comprehensive Python library for profiling CPU, disk, memory, network I/O, and function calls with integrated visualization.
Home-page: https://github.com/vigsun19/smartprofiler
Author: Vignesh Sundaram
Author-email: vigneshanm@gmail.com
License: MIT
Classifier: Programming Language :: Python :: 3
Classifier: Programming Language :: Python :: 3.8
Classifier: Programming Language :: Python :: 3.9
Classifier: Programming Language :: Python :: 3.10
Classifier: Programming Language :: Python :: 3.11
Classifier: Programming Language :: Python :: 3.12
Classifier: License :: OSI Approved :: MIT License
Classifier: Operating System :: OS Independent
Requires-Python: >=3.8
Requires-Dist: matplotlib>=3.5.0
Requires-Dist: numpy>=1.21.0
Requires-Dist: requests>=2.28.0
Requires-Dist: psutil>=5.9.0
